{
  "classname": "CCNode",
  "name": null,
  "canedit": true,
  "objecttag": 10000,
  "rotation": 0,
  "scalex": 1,
  "scaley": 1,
  "visible": 1,
  "x": 0,
  "y": 0,
  "zorder": 1,
  "gameobjects": [
    {
      "__type": "ComGameObjectSurrogate:#EditorCommon.JsonModel",
      "classname": "CCNode",
      "name": "bg1",
      "canedit": false,
      "objecttag": 10003,
      "rotation": 0,
      "scalex": 1,
      "scaley": 1,
      "visible": 1,
      "x": 479,
      "y": 324,
      "zorder": 1,
      "gameobjects": [],
      "components": [
        {
          "__type": "ComSpriteSurrogate:#EditorCommon.JsonModel.Component",
          "classname": "CCSprite",
          "name": "CCSprite",
          "file": null,
          "fileData": {
            "path": "img/bg1.png",
            "plistFile": null,
            "resourceType": 0
          }
        }
      ]
    },
    {
      "__type": "ComGameObjectSurrogate:#EditorCommon.JsonModel",
      "classname": "CCNode",
      "name": null,
      "canedit": true,
      "objecttag": 10014,
      "rotation": 0,
      "scalex": 1,
      "scaley": 1,
      "visible": 1,
      "x": 476,
      "y": 316,
      "zorder": 1,
      "gameobjects": [],
      "components": [
        {
          "__type": "ComGUIAdapterSurrogate:#EditorCommon.JsonModel.Component",
          "classname": "GUIComponent",
          "name": "GUIComponent",
          "file": null,
          "fileData": {
            "path": "ui/DemoHead_UI/DemoHead_UI.json",
            "plistFile": null,
            "resourceType": 0
          }
        }
      ]
    },
    {
      "__type": "ComGameObjectSurrogate:#EditorCommon.JsonModel",
      "classname": "CCNode",
      "name": null,
      "canedit": true,
      "objecttag": 10015,
      "rotation": 0,
      "scalex": 1,
      "scaley": 1,
      "visible": 1,
      "x": 472,
      "y": 183,
      "zorder": 1,
      "gameobjects": [],
      "components": [
        {
          "__type": "ComGUIAdapterSurrogate:#EditorCommon.JsonModel.Component",
          "classname": "GUIComponent",
          "name": "GUIComponent",
          "file": null,
          "fileData": {
            "path": "ui/SkillMenu_1/SkillMenu_1.json",
            "plistFile": null,
            "resourceType": 0
          }
        }
      ]
    }
  ],
  "CanvasSize": {
    "_height": 640,
    "_width": 960
  },
  "Version": "1.1.0.0",
  "components": [
    {
      "__type": "ComSceneSurrogate:#EditorCommon.JsonModel.Component",
      "classname": "CCScene",
      "name": "CCScene",
      "scenename": "FightScene"
    },
    {
      "__type": "ComSimpleAudioSurrogate:#EditorCommon.JsonModel.Component",
      "classname": "CCBackgroundAudio",
      "name": "CCBackgroundAudio",
      "file": null,
      "fileData": {
        "path": "sound/arena.mp3",
        "plistFile": null,
        "resourceType": 0
      },
      "loop": 1
    }
  ]
}